LICENSE.txt
MANIFEST.in
README.md
setup.py
qutil/__init__.py
qutil/app.py
qutil.egg-info/PKG-INFO
qutil.egg-info/SOURCES.txt
qutil.egg-info/dependency_links.txt
qutil.egg-info/requires.txt
qutil.egg-info/top_level.txt
qutil/database/__init__.py
qutil/database/actions.py
qutil/database/connection.py
qutil/sql/createDB.sql
qutil/sql/createTable.sql
qutil/sql/dropDB.sql
qutil/sql/rawFile.sql
qutil/sql/useDB.sql
test/test.py