Metadata-Version: 2.1
Name: qutil
Version: 1.0a2
Summary: Query utils for structured databases
Home-page: https://github.com/julian4u0/qutil
License: UNKNOWN
Project-URL: Bug Reports, https://github.com/julian4u0/qutil/issues
Project-URL: Source, https://github.com/julian4u0/qutil
Keywords: sql,mysql,utils,util,helper
Platform: UNKNOWN
Classifier: Development Status :: 3 - Alpha
Classifier: Intended Audience :: Developers
Classifier: Topic :: Software Development :: Build Tools
Classifier: License :: OSI Approved :: MIT License
Classifier: Programming Language :: Python :: 3
Classifier: Programming Language :: Python :: 3.6
Classifier: Programming Language :: Python :: 3.7
Classifier: Programming Language :: Python :: 3.8
Classifier: Programming Language :: Python :: 3.9
Classifier: Programming Language :: Python :: 3 :: Only
Requires-Python: >=3.7
